QianchuanDataCollection/__init__.py
QianchuanDataCollection/_browser_utils.py
QianchuanDataCollection/_types.py
QianchuanDataCollection/_utils.py
QianchuanDataCollection/collector.py
QianchuanDataCollection/data/_dict.py
QianchuanDataCollection/data/_utils.py
QianchuanDataCollection/data/data.py
QianchuanDataCollection/data/material.py
QianchuanDataCollection/data/site_promotion.py
qianchuan_data_collection-1.0.7.dist-info/LICENSE
qianchuan_data_collection-1.0.7.dist-info/METADATA
qianchuan_data_collection-1.0.7.dist-info/WHEEL
qianchuan_data_collection-1.0.7.dist-info/RECORD
