Metadata-Version: 2.1
Name: qianchuan-data-collection
Version: 1.0.7
Summary: Qianchuan data collection
License: MIT
Author: martianbugs
Requires-Python: >=3.9
Classifier: License :: OSI Approved :: MIT License
Classifier: Programming Language :: Python :: 3
Classifier: Programming Language :: Python :: 3.9
Classifier: Programming Language :: Python :: 3.10
Classifier: Programming Language :: Python :: 3.11
Classifier: Programming Language :: Python :: 3.12
Requires-Dist: drissionpage (>=4.1.0.17,<5.0.0.0)
